LICENSE
MANIFEST.in
NOTICE
README.rst
httpie_plex.py
setup.py
httpie_plex.egg-info/PKG-INFO
httpie_plex.egg-info/SOURCES.txt
httpie_plex.egg-info/dependency_links.txt
httpie_plex.egg-info/entry_points.txt
httpie_plex.egg-info/not-zip-safe
httpie_plex.egg-info/requires.txt
httpie_plex.egg-info/top_level.txt