Metadata-Version: 1.1
Name: httpie-plex
Version: 1.0.1
Summary: Auth plugin for HTTPie for MediaMath's Plex.
Home-page: https://github.com/MediaMath/httpie-plex
Author: Prasanna Swaminathan
Author-email: prasanna@mediamath.com
License:                                  Apache License
